MANIFEST.in
README
setup.py
pandas_qt.egg-info/PKG-INFO
pandas_qt.egg-info/SOURCES.txt
pandas_qt.egg-info/dependency_links.txt
pandas_qt.egg-info/namespace_packages.txt
pandas_qt.egg-info/requires.txt
pandas_qt.egg-info/top_level.txt
pandasqt/__init__.py
pandasqt/compat.py
pandasqt/encoding.py
pandasqt/excepthook.py
pandasqt/utils.py
pandasqt/_lib/magic/libgcc_s_dw2-1.dll
pandasqt/_lib/magic/libmagic-1.dll
pandasqt/_lib/magic/libregex-1.dll
pandasqt/_lib/magic/magic1.dll
pandasqt/_lib/magic/zlib1.dll
pandasqt/_lib/magic/db/magic.mgc
pandasqt/i18n/de.qm
pandasqt/models/ColumnDtypeModel.py
pandasqt/models/DataFrameModel.py
pandasqt/models/DataSearch.py
pandasqt/models/ProgressThread.py
pandasqt/models/SupportedDtypes.py
pandasqt/models/__init__.py
pandasqt/models/mime.py
pandasqt/ui/__init__.py
pandasqt/ui/fallback/__init__.py
pandasqt/ui/fallback/easygui/__init__.py
pandasqt/ui/fallback/easygui/easygui.py
pandasqt/ui/fallback/easygui/boxes/__init__.py
pandasqt/ui/fallback/easygui/boxes/about.py
pandasqt/ui/fallback/easygui/boxes/base_boxes.py
pandasqt/ui/fallback/easygui/boxes/derived_boxes.py
pandasqt/ui/fallback/easygui/boxes/egstore.py
pandasqt/ui/fallback/easygui/boxes/state.py
pandasqt/ui/fallback/easygui/boxes/text_box.py
pandasqt/ui/fallback/easygui/boxes/updatable_text_box.py
pandasqt/ui/fallback/easygui/boxes/utils.py
pandasqt/views/BigIntSpinbox.py
pandasqt/views/CSVDialogs.py
pandasqt/views/CustomDelegates.py
pandasqt/views/DataTableView.py
pandasqt/views/EditDialogs.py
pandasqt/views/OverlayProgressView.py
pandasqt/views/__init__.py
pandasqt/views/_ui/__init__.py
pandasqt/views/_ui/icons_rc.py