Metadata-Version: 1.1
Name: pandas-qt
Version: 0.2.0
Summary: Utilities to use pandas (the data analysis / manipulation library for Python) with Qt.
Home-page: https://github.com/datalyze-solutions/pandas-qt
Author: Matthias Ludwig, Marcel Radischat
Author-email: m.Ludwig@datalyze-solutions.com
License: MIT License
Platform: any
Classifier: Programming Language :: Python
Classifier: Development Status :: 4 - Beta
Classifier: Natural Language :: German
Classifier: Environment :: X11 Applications :: Qt
Classifier: Intended Audience :: Developers
Classifier: License :: OSI Approved :: BSD License
Classifier: Operating System :: OS Independent
Classifier: Topic :: Software Development :: Libraries :: Python Modules
Classifier: Topic :: Software Development :: User Interfaces
